{
  "slug": "2026-W14",
  "title": "Week of March 30, 2026",
  "summary": "This week focused on platform stability improvements that ensure more reliable Salesforce deployments and automation workflows. We enhanced Salesforce deployment validation to better detect configuration issues and improved the overall reliability of platform updates and integrations.",
  "published_at": "2026-04-01T19:04:45.559Z",
  "week_start": "2026-03-30",
  "week_end": "2026-04-01",
  "has_breaking": false,
  "total_commits": 74,
  "entries": [
    {
      "category": "improved",
      "plugin": "Core Platform",
      "headline": "Platform updates now include latest marketplace features",
      "details": null,
      "commits": [
        "d4d0188"
      ]
    },
    {
      "category": "improved",
      "plugin": "Salesforce",
      "headline": "Better Salesforce deployment validation and error detection",
      "details": [
        "Automatically detects State and Country field configuration issues that could break workflows",
        "Improved deployment validation checks prevent common setup problems",
        "Enhanced error recovery for more reliable deployments"
      ],
      "commits": [
        "fcad945"
      ]
    },
    {
      "category": "improved",
      "plugin": "Salesforce",
      "headline": "More reliable Salesforce multi-step deployments",
      "details": null,
      "commits": [
        "a1075f7"
      ]
    },
    {
      "category": "fixed",
      "plugin": "HubSpot",
      "headline": "Resolved HubSpot automation startup issues",
      "details": null,
      "commits": [
        "c53235d"
      ]
    }
  ]
}
